[
  {
    "id": "hosp-gansu-001",
    "name": "临夏州人民医院",
    "province": "甘肃",
    "provinceFullName": "甘肃省",
    "city": "临夏回族",
    "cityFullName": "临夏回族自治州",
    "region": "西北",
    "level": "三级甲等",
    "aliases": [],
    "featured": false
  },
  {
    "id": "hosp-gansu-002",
    "name": "兰州大学口腔医院",
    "province": "甘肃",
    "provinceFullName": "甘肃省",
    "city": "兰州",
    "cityFullName": "兰州市",
    "region": "西北",
    "level": "三级甲等",
    "aliases": [],
    "featured": false
  },
  {
    "id": "hosp-gansu-003",
    "name": "兰州大学第一医院",
    "province": "甘肃",
    "provinceFullName": "甘肃省",
    "city": "兰州",
    "cityFullName": "兰州市",
    "region": "西北",
    "level": "三级甲等",
    "aliases": [],
    "featured": false
  },
  {
    "id": "hosp-gansu-004",
    "name": "兰州大学第二医院",
    "province": "甘肃",
    "provinceFullName": "甘肃省",
    "city": "兰州",
    "cityFullName": "兰州市",
    "region": "西北",
    "level": "三级甲等",
    "aliases": [],
    "featured": false
  },
  {
    "id": "hosp-gansu-005",
    "name": "兰州市第一人民医院",
    "province": "甘肃",
    "provinceFullName": "甘肃省",
    "city": "兰州",
    "cityFullName": "兰州市",
    "region": "西北",
    "level": "三级甲等",
    "aliases": [],
    "featured": false
  },
  {
    "id": "hosp-gansu-006",
    "name": "兰州市第二人民医院",
    "province": "甘肃",
    "provinceFullName": "甘肃省",
    "city": "兰州",
    "cityFullName": "兰州市",
    "region": "西北",
    "level": "三级甲等",
    "aliases": [],
    "featured": false
  },
  {
    "id": "hosp-gansu-007",
    "name": "嘉峪关市第一人民医院",
    "province": "甘肃",
    "provinceFullName": "甘肃省",
    "city": "嘉峪关",
    "cityFullName": "嘉峪关市",
    "region": "西北",
    "level": "三级甲等",
    "aliases": [],
    "featured": false
  },
  {
    "id": "hosp-gansu-008",
    "name": "天水市中医医院",
    "province": "甘肃",
    "provinceFullName": "甘肃省",
    "city": "天水",
    "cityFullName": "天水市",
    "region": "西北",
    "level": "三级甲等",
    "aliases": [],
    "featured": false
  },
  {
    "id": "hosp-gansu-009",
    "name": "天水市第一人民医院",
    "province": "甘肃",
    "provinceFullName": "甘肃省",
    "city": "天水",
    "cityFullName": "天水市",
    "region": "西北",
    "level": "三级甲等",
    "aliases": [],
    "featured": false
  },
  {
    "id": "hosp-gansu-010",
    "name": "天水市第三人民医院",
    "province": "甘肃",
    "provinceFullName": "甘肃省",
    "city": "天水",
    "cityFullName": "天水市",
    "region": "西北",
    "level": "三级甲等",
    "aliases": [],
    "featured": false
  },
  {
    "id": "hosp-gansu-011",
    "name": "天水市第二人民医院",
    "province": "甘肃",
    "provinceFullName": "甘肃省",
    "city": "天水",
    "cityFullName": "天水市",
    "region": "西北",
    "level": "三级甲等",
    "aliases": [],
    "featured": false
  },
  {
    "id": "hosp-gansu-012",
    "name": "定西市人民医院",
    "province": "甘肃",
    "provinceFullName": "甘肃省",
    "city": "定西",
    "cityFullName": "定西市",
    "region": "西北",
    "level": "三级甲等",
    "aliases": [],
    "featured": false
  },
  {
    "id": "hosp-gansu-013",
    "name": "平凉市人民医院",
    "province": "甘肃",
    "provinceFullName": "甘肃省",
    "city": "平凉",
    "cityFullName": "平凉市",
    "region": "西北",
    "level": "三级甲等",
    "aliases": [],
    "featured": false
  },
  {
    "id": "hosp-gansu-014",
    "name": "庆阳市中医医院",
    "province": "甘肃",
    "provinceFullName": "甘肃省",
    "city": "庆阳",
    "cityFullName": "庆阳市",
    "region": "西北",
    "level": "三级甲等",
    "aliases": [],
    "featured": false
  },
  {
    "id": "hosp-gansu-015",
    "name": "庆阳市人民医院",
    "province": "甘肃",
    "provinceFullName": "甘肃省",
    "city": "庆阳",
    "cityFullName": "庆阳市",
    "region": "西北",
    "level": "三级甲等",
    "aliases": [],
    "featured": false
  },
  {
    "id": "hosp-gansu-016",
    "name": "张掖市人民医院",
    "province": "甘肃",
    "provinceFullName": "甘肃省",
    "city": "张掖",
    "cityFullName": "张掖市",
    "region": "西北",
    "level": "三级甲等",
    "aliases": [],
    "featured": false
  },
  {
    "id": "hosp-gansu-017",
    "name": "张掖市第二人民医院",
    "province": "甘肃",
    "provinceFullName": "甘肃省",
    "city": "张掖",
    "cityFullName": "张掖市",
    "region": "西北",
    "level": "三级甲等",
    "aliases": [],
    "featured": false
  },
  {
    "id": "hosp-gansu-018",
    "name": "武威市中医医院",
    "province": "甘肃",
    "provinceFullName": "甘肃省",
    "city": "武威",
    "cityFullName": "武威市",
    "region": "西北",
    "level": "三级甲等",
    "aliases": [],
    "featured": false
  },
  {
    "id": "hosp-gansu-019",
    "name": "武威市人民医院",
    "province": "甘肃",
    "provinceFullName": "甘肃省",
    "city": "武威",
    "cityFullName": "武威市",
    "region": "西北",
    "level": "三级甲等",
    "aliases": [],
    "featured": false
  },
  {
    "id": "hosp-gansu-020",
    "name": "武威肿瘤医院",
    "province": "甘肃",
    "provinceFullName": "甘肃省",
    "city": "武威",
    "cityFullName": "武威市",
    "region": "西北",
    "level": "三级甲等",
    "aliases": [],
    "featured": false
  },
  {
    "id": "hosp-gansu-021",
    "name": "甘肃中医药大学附属医院",
    "province": "甘肃",
    "provinceFullName": "甘肃省",
    "city": "兰州",
    "cityFullName": "兰州市",
    "region": "西北",
    "level": "三级甲等",
    "aliases": [],
    "featured": false
  },
  {
    "id": "hosp-gansu-022",
    "name": "甘肃宝石花医院",
    "province": "甘肃",
    "provinceFullName": "甘肃省",
    "city": "兰州",
    "cityFullName": "兰州市",
    "region": "西北",
    "level": "三级甲等",
    "aliases": [
      "兰州石化总医院"
    ],
    "featured": false
  },
  {
    "id": "hosp-gansu-023",
    "name": "甘肃省中医院",
    "province": "甘肃",
    "provinceFullName": "甘肃省",
    "city": "兰州",
    "cityFullName": "兰州市",
    "region": "西北",
    "level": "三级甲等",
    "aliases": [],
    "featured": false
  },
  {
    "id": "hosp-gansu-024",
    "name": "甘肃省人民医院",
    "province": "甘肃",
    "provinceFullName": "甘肃省",
    "city": "兰州",
    "cityFullName": "兰州市",
    "region": "西北",
    "level": "三级甲等",
    "aliases": [],
    "featured": false
  },
  {
    "id": "hosp-gansu-025",
    "name": "甘肃省妇幼保健院",
    "province": "甘肃",
    "provinceFullName": "甘肃省",
    "city": "兰州",
    "cityFullName": "兰州市",
    "region": "西北",
    "level": "三级甲等",
    "aliases": [],
    "featured": false
  },
  {
    "id": "hosp-gansu-026",
    "name": "甘肃省康复中心医院",
    "province": "甘肃",
    "provinceFullName": "甘肃省",
    "city": "兰州",
    "cityFullName": "兰州市",
    "region": "西北",
    "level": "三级甲等",
    "aliases": [],
    "featured": false
  },
  {
    "id": "hosp-gansu-027",
    "name": "甘肃省第三人民医院",
    "province": "甘肃",
    "provinceFullName": "甘肃省",
    "city": "兰州",
    "cityFullName": "兰州市",
    "region": "西北",
    "level": "三级甲等",
    "aliases": [],
    "featured": false
  },
  {
    "id": "hosp-gansu-028",
    "name": "甘肃省第二人民医院",
    "province": "甘肃",
    "provinceFullName": "甘肃省",
    "city": "兰州",
    "cityFullName": "兰州市",
    "region": "西北",
    "level": "三级甲等",
    "aliases": [],
    "featured": false
  },
  {
    "id": "hosp-gansu-029",
    "name": "甘肃省肿瘤医院",
    "province": "甘肃",
    "provinceFullName": "甘肃省",
    "city": "兰州",
    "cityFullName": "兰州市",
    "region": "西北",
    "level": "三级甲等",
    "aliases": [],
    "featured": false
  },
  {
    "id": "hosp-gansu-030",
    "name": "酒泉市人民医院",
    "province": "甘肃",
    "provinceFullName": "甘肃省",
    "city": "酒泉",
    "cityFullName": "酒泉市",
    "region": "西北",
    "level": "三级甲等",
    "aliases": [],
    "featured": false
  },
  {
    "id": "hosp-gansu-031",
    "name": "酒钢医院",
    "province": "甘肃",
    "provinceFullName": "甘肃省",
    "city": "嘉峪关",
    "cityFullName": "嘉峪关市",
    "region": "西北",
    "level": "三级甲等",
    "aliases": [],
    "featured": false
  },
  {
    "id": "hosp-gansu-032",
    "name": "金川集团职工医院",
    "province": "甘肃",
    "provinceFullName": "甘肃省",
    "city": "金昌",
    "cityFullName": "金昌市",
    "region": "西北",
    "level": "三级甲等",
    "aliases": [],
    "featured": false
  },
  {
    "id": "hosp-gansu-033",
    "name": "陇南市第一人民医院",
    "province": "甘肃",
    "provinceFullName": "甘肃省",
    "city": "陇南",
    "cityFullName": "陇南市",
    "region": "西北",
    "level": "三级甲等",
    "aliases": [],
    "featured": false
  }
]
